marshmallow_peewee/__init__.py
marshmallow_peewee/config.py
marshmallow_peewee/convert.py
marshmallow_peewee/fields.py
marshmallow_peewee/py.typed
marshmallow_peewee/schema.py
marshmallow_peewee/types.py
marshmallow_peewee-5.0.0.dist-info/METADATA
marshmallow_peewee-5.0.0.dist-info/WHEEL
marshmallow_peewee-5.0.0.dist-info/RECORD
