Metadata-Version: 2.1
Name: marshmallow-peewee
Version: 5.0.0
Summary: Peewee ORM integration with the Marshmallow (de)serialization library
Home-page: https://github.com/klen/marshmallow-peewee
License: MIT
Keywords: marshmallow,peewee,orm,serialization,deserialization
Author: Kirill Klenov
Author-email: horneds@gmail.com
Requires-Python: >=3.9,<4.0
Classifier: Development Status :: 5 - Production/Stable
Classifier: Intended Audience :: Developers
Classifier: License :: OSI Approved :: MIT License
Classifier: Programming Language :: Python
Classifier: Programming Language :: Python :: 3
Classifier: Programming Language :: Python :: 3.9
Classifier: Programming Language :: Python :: 3.10
Classifier: Programming Language :: Python :: 3.11
Classifier: Programming Language :: Python :: 3.12
Classifier: Programming Language :: Python :: 3.13
Requires-Dist: marshmallow (>=3.0.0,<4.0.0)
Requires-Dist: peewee (>=3.14.0,<4.0.0)
Project-URL: Repository, https://github.com/klen/marshmallow-peewee
